{
  "broker": "21",
  "date": "2026-05-12",
  "symbols": [
    {
      "symbol": "NICL",
      "buy_qty": 50.0,
      "buy_amount": 57056.69,
      "sell_qty": 5510.0,
      "sell_amount": 2464848.86,
      "net_qty": -5460.0,
      "net_amount": -2407792.17
    },
    {
      "symbol": "UPPER",
      "buy_qty": 8060.0,
      "buy_amount": 7499457.079999999,
      "sell_qty": 1100.0,
      "sell_amount": 1491247.3299999998,
      "net_qty": 6960.0,
      "net_amount": 6008209.749999999
    },
    {
      "symbol": "GBIME",
      "buy_qty": 5630.0,
      "buy_amount": 5580870.819999999,
      "sell_qty": 5150.0,
      "sell_amount": 5501426.210000001,
      "net_qty": 480.0,
      "net_amount": 79444.60999999847
    },
    {
      "symbol": "NABIL",
      "buy_qty": 2100.0,
      "buy_amount": 1958359.67,
      "sell_qty": 10050.0,
      "sell_amount": 9765269.32,
      "net_qty": -7950.0,
      "net_amount": -7806909.65
    },
    {
      "symbol": "SHL",
      "buy_qty": 1010.0,
      "buy_amount": 843632.5599999999,
      "sell_qty": 0.0,
      "sell_amount": 0.0,
      "net_qty": 1010.0,
      "net_amount": 843632.5599999999
    },
    {
      "symbol": "HRL",
      "buy_qty": 1160.0,
      "buy_amount": 960176.9299999999,
      "sell_qty": 510.0,
      "sell_amount": 507058.3,
      "net_qty": 650.0,
      "net_amount": 453118.62999999995
    },
    {
      "symbol": "HDL",
      "buy_qty": 1000.0,
      "buy_amount": 1400351.19,
      "sell_qty": 6500.0,
      "sell_amount": 8501977.41,
      "net_qty": -5500.0,
      "net_amount": -7101626.220000001
    },
    {
      "symbol": "NTC",
      "buy_qty": 2300.0,
      "buy_amount": 2652253.6099999994,
      "sell_qty": 1060.0,
      "sell_amount": 1201567.92,
      "net_qty": 1240.0,
      "net_amount": 1450685.6899999995
    },
    {
      "symbol": "PCBL",
      "buy_qty": 0.0,
      "buy_amount": 0.0,
      "sell_qty": 50.0,
      "sell_amount": 35298.1,
      "net_qty": -50.0,
      "net_amount": -35298.1
    },
    {
      "symbol": "STC",
      "buy_qty": 0.0,
      "buy_amount": 0.0,
      "sell_qty": 5150.0,
      "sell_amount": 6497560.97,
      "net_qty": -5150.0,
      "net_amount": -6497560.97
    }
  ]
}